dft_phot1x/DFT.xml
dft_phot1x/__init__.py
dft_phot1x-0.1.1.dist-info/licenses/LICENSE.md
dft_phot1x-0.1.1.dist-info/METADATA
dft_phot1x-0.1.1.dist-info/WHEEL
dft_phot1x-0.1.1.dist-info/top_level.txt
dft_phot1x-0.1.1.dist-info/RECORD
