Metadata-Version: 2.4
Name: dft_phot1x
Version: 0.1.1
Summary: Design for Test rules for the edX UBCx Phot1x course, using the SiEPIC_EBeam_PDK process design kit (PDK) for silicon photonics fabrication. 
Author-email: Lukas Chrostowski <lukasc@ece.ubc.ca>
Project-URL: Homepage, https://github.com/SiEPIC/DFT_Phot1x
Project-URL: Issues, https://github.com/SiEPIC/DFT_Phot1x/issues
Classifier: Programming Language :: Python :: 3
Classifier: License :: OSI Approved :: MIT License
Classifier: Operating System :: OS Independent
Requires-Python: >=3.8
License-File: LICENSE.md
Dynamic: license-file
